LICENSE
README.md
pyproject.toml
setup.cfg
setup.py
lintlizard/__init__.py
lintlizard.egg-info/PKG-INFO
lintlizard.egg-info/SOURCES.txt
lintlizard.egg-info/dependency_links.txt
lintlizard.egg-info/entry_points.txt
lintlizard.egg-info/requires.txt
lintlizard.egg-info/top_level.txt