Metadata-Version: 2.1
Name: lintlizard
Version: 0.21.0
Summary: Run various linters to ensure a common code quality baseline
Home-page: https://github.com/closeio/lintlizard
Author: Vyacheslav Tverskoy
Author-email: v@close.com
License: UNKNOWN
Platform: UNKNOWN
Classifier: Intended Audience :: Developers
Classifier: Programming Language :: Python :: 3
Classifier: License :: OSI Approved :: MIT License
Classifier: Operating System :: POSIX
Requires-Python: >=3.7
License-File: LICENSE
